{"job_title": ["Advisory - Consulting ACOE - Cloud Developer", "Senior Cloud Engineer", "Application Developer: IBM Cloud FullStack", "Multi-Cloud Kubernetes Engineer Senior", "Lead Engineer Cloud Computing", "Informatica Intelligent Cloud Services Application Developer", "Director S/W Engineering - Cloud Architecture, Java", "Salesforce Sales Cloud Application Developer", "Senior Cloud Engineer", "IT Manager", "Java Architect", "Technical Architect Senior", "Associate Architect", "Telecom BSS Architect", "Senior DevOps Architect", "Technical Architect", "Senior Architect , Data Portability", "Technical Architect", "Senior Technical Architect", "Architect ( ATC )", "Architect ( Customer Facing )", "Python Architect", "GCP Architect", "Information Security Architect", "Architect Kubernetes-CKS", "Architect", "IT Architect, Sr II", "Senior DevSecOps Architect", "SAP Business Planning and Consolidation Business Process Architect", "SAP S/4HANA Group Reporting Business Process Architect", "Solution Architect - Azure Devops", "Cloud Engineer Trainee", "Consulting Role - IT Cloud - Azure/AWS/GCP", "AWS Solutions Architect", "Cloud Engineer (AWS/Azure)", "Cloud Solution Specialist-Infra", ".Net Senior Solution Architect-14-18Y-Bangalore-PWC SDC", "Azure Cloud Admin", "Sr. Technology Architect", "Presales Solution Architect", "Azure Cloud Administrator L2", "Digital Solutions Architect (Global)", "Test - Solution Architect", "Solution Architecting Solution Planner", "Solution Architect", "Salesforce Solution Architect - Apex/JavaScript", "Azure Cloud Engineer", "AWS/Azure Architect", "Hiring Cyber Security Solutions Architect For Mumbai-Andheri Loction", "Solution Architect", "Looking For Azure Cloud & AI Full Stack Engineer"], "company_name": ["PwC", "EA Games (Electronic Arts)", "IBM", "Siemens", "Quality Engineering Software Technologies Pvt. Ltd.", "Accenture", "Optum", "Accenture", "ASSA ABLOY Opening Solutions", "Group Bayport", "Zensar", "CGI", "Virtusa", "CGI", "Ness", "Oracle", "Atlassian", "PayU", "PayU", "Virtusa", "Virtusa", "CSS Corp", "CGI", "Arrow Electronics", "Rakuten, Inc.", "Infogain India (P) Ltd.", "Synopsys (India) Private Limited", "CGI", "Accenture", "Accenture", "CitiusTech", "G7 CR Technologies India Pvt. Ltd.", "Elixir Web Solutions", "GM WARE", "TRH Consultancy Services", "Hucon Solutions (India) Ptd Ltd", "PwC", "Diverse Lynx", "Opentext", "Visionet Systems", "MOURI Tech", "Siemens", "Capgemini", "Accenture", "Manipal Global Education", "Marktine", "Neudesic Technologies -An IBM Company", "CC Staffing International", "WRITER BUSINESS SERVICES PVT LTD", "Birlasoft", "Skandha It Services"], "company_rating": ["3.8", "4.6", "4.2", "4.2", "3.6", "4.2", "4.1", "4.2", "4.2", "3.9", "3.9", "4.2", "3.8", "4.2", "3.7", "3.9", "4.2", "4.2", "4.2", "3.8", "3.8", "3.7", "4.2", "3.7", "4.1", "3.9", "4.2", "4.2", "4.2", "4.2", "4.0", "3.3", "Not Found", "4.8", "Not Found", "Not Found", "3.8", "3.2", "4.0", "3.4", "4.0", "4.2", "3.9", "4.2", "4.1", "4.6", "Not Found", "Not Found", "3.8", "3.8", "Not Found"], "company_review_count": ["(3794 Reviews)", "(22 Reviews)", "(20453 Reviews)", "(4676 Reviews)", "(926 Reviews)", "(30523 Reviews)", "(1940 Reviews)", "(30523 Reviews)", "(59 Reviews)", "(68 Reviews)", "(1429 Reviews)", "(2177 Reviews)", "(2030 Reviews)", "(2177 Reviews)", "(310 Reviews)", "(3707 Reviews)", "(14 Reviews)", "(213 Reviews)", "(213 Reviews)", "(2030 Reviews)", "(2030 Reviews)", "(1121 Reviews)", "(2177 Reviews)", "(289 Reviews)", "(141 Reviews)", "(586 Reviews)", "(146 Reviews)", "(2177 Reviews)", "(30523 Reviews)", "(30523 Reviews)", "(688 Reviews)", "(108 Reviews)", "Not Found", "(26 Reviews)", "Not Found", "Not Found", "(3794 Reviews)", "(72 Reviews)", "(288 Reviews)", "(523 Reviews)", "(232 Reviews)", "(4676 Reviews)", "(22433 Reviews)", "(30523 Reviews)", "(85 Reviews)", "(15 Reviews)", "Not Found", "Not Found", "(117 Reviews)", "(1359 Reviews)", "Not Found"], "experience": ["10-15 Yrs", "8-13 Yrs", "6-10 Yrs", "3-7 Yrs", "4-9 Yrs", "12-15 Yrs", "8-13 Yrs", "8-10 Yrs", "8-10 Yrs", "5-10 Yrs", "8-13 Yrs", "7-12 Yrs", "4-7 Yrs", "8-13 Yrs", "9-14 Yrs", "10-17 Yrs", "11-13 Yrs", "8-13 Yrs", "12-17 Yrs", "6-9 Yrs", "4-8 Yrs", "10-20 Yrs", "6-11 Yrs", "5-8 Yrs", "4-7 Yrs", "16-18 Yrs", "5-8 Yrs", "7-11 Yrs", "8-10 Yrs", "4-6 Yrs", "7-14 Yrs", "0-3 Yrs", "10-20 Yrs", "4-9 Yrs", "5-10 Yrs", "5-8 Yrs", "14-20 Yrs", "5-8 Yrs", "7-12 Yrs", "7-12 Yrs", "6-11 Yrs", "4-10 Yrs", "14-16 Yrs", "8-10 Yrs", "8-13 Yrs", "8-12 Yrs", "4-9 Yrs", "12-17 Yrs", "5-8 Yrs", "12-14 Yrs", "4-8 Yrs"], "salary": ["Not disclosed", "Not disclosed", "Not disclosed", "Not disclosed", "Not disclosed", "Not disclosed", "Not disclosed", "Not disclosed", "Not disclosed", "Not disclosed", "Not disclosed", "Not disclosed", "Not disclosed", "Not disclosed", "20,00,000 - 35,00,000 PA.", "Not disclosed", "Not disclosed", "Not disclosed", "Not disclosed", "Not disclosed", "Not disclosed", "Not disclosed", "Not disclosed", "Not disclosed", "Not disclosed", "Not disclosed", "Not disclosed", "Not disclosed", "Not disclosed", "Not disclosed", "Not disclosed", "Not disclosed", "Not disclosed", "Not disclosed", "Not disclosed", "Not disclosed", "Not disclosed", "Not disclosed", "Not disclosed", "Not disclosed", "Not disclosed", "Not disclosed", "Not disclosed", "Not disclosed", "15,00,000 - 25,00,000 PA.", "Not disclosed", "Not disclosed", "Not disclosed", "12,00,000 - 16,00,000 PA.", "Not disclosed", "Not disclosed"], "location": ["Hyderabad/Secunderabad", "Hyderabad/Secunderabad", "Hyderabad/Secunderabad", "Hyderabad/Secunderabad, Pune", "Trivandrum/Thiruvananthapuram", "Hyderabad/Secunderabad", "Hyderabad/Secunderabad", "Delhi / NCR", "Chennai", "Ahmedabad(Usmanpura)", "Hyderabad/Secunderabad, Pune, Bangalore/Bengaluru", "Bangalore/Bengaluru", "Bangalore/Bengaluru", "Bangalore/Bengaluru", "Hyderabad/Secunderabad, Bangalore/Bengaluru, Mumbai (All Areas)", "Mumbai, Pune, Mumbai (All Areas)", "Bangalore/Bengaluru", "Bangalore/Bengaluru", "Bangalore/Bengaluru", "Bangalore/Bengaluru", "Bangalore/Bengaluru", "Hyderabad/Secunderabad, Chennai, Bangalore/Bengaluru", "Bangalore/Bengaluru", "Bangalore/Bengaluru", "Bangalore/Bengaluru", "Bangalore/Bengaluru", "Bangalore/Bengaluru", "Bangalore/Bengaluru", "Pune", "Pune", "Mumbai, Pune, Chennai, Bangalore/Bengaluru", "Bangalore/Bengaluru", "Mumbai, Gurgaon/Gurugram, Bangalore/Bengaluru", "Mohali", "Mumbai, New Delhi, Hyderabad/Secunderabad, Pune, Chennai, Gurgaon/Gurugram, Bangalore/Bengaluru", "Navi Mumbai", "Bangalore/Bengaluru", "Bangalore/Bengaluru", "Hyderabad/Secunderabad", "Bangalore/Bengaluru", "Visakhapatnam, Hyderabad/Secunderabad, Bangalore/Bengaluru", "Bangalore/Bengaluru", "Bangalore/Bengaluru", "Bangalore/Bengaluru", "Bangalore/Bengaluru", "Kolkata, Mumbai, Hyderabad/Secunderabad, Lucknow, Chennai, Ahmedabad, Delhi / NCR, Bangalore/Bengaluru", "Kochi/Cochin, Kolkata, Pune, Chennai, Bangalore/Bengaluru, Delhi / NCR, Mumbai (All Areas)", "Hyderabad", "Mumbai(Marol)", "Pune", "Hyderabad/Secunderabad, Chennai, Bangalore/Bengaluru"], "job_description": ["Main purpose of the job and key background information Building Cloud capabilities incl...", "You will propose innovative solutions and improve existing systems to increase efficien...", "As an Application Developer, you will lead IBM into the future by translating system re...", "Overview: As a senior Multi-Cloud Kubernetes Infrastructure Engineer, you\u2019ll apply spec...", "Roles Responsibilities Must be able to work independently and take ownership Work proac...", "Educational Qualification : 15 year full time education or BE Work Experience : 12-15 y...", "Undergraduate degree or equivalent experience Hands on experience with building cloud n...", "Educational Qualification : 15 years of full time education Bachelor / Masters universi...", "Undergraduate degree in Information Technology, Computer Science, Engineering, or a rel...", "Must be a good problem solver Should work towards making the company network secure fro...", "Note - Only Immediate Joiners or less notice period can apply for this roleExperience -...", "Institute infrastructure as code, security automation and automation or routine mainten...", "Lead the cloud architecture work for multiple applications.Bring thought leadership in ...", "Position Description:The ideal candidates will work in a highly dynamic and fast-paced ...", "A bachelors degree in engineering Experience working in globally distributed teams 10 y...", "OFSS Consulting is part of Financial Services Global unit and provides a variety of con...", "You will be a role model for, and influence a large team of engineers at various senior...", "Programming experience with modern SaaS, contributing to the architecture and design (s...", "Requirements At a senior role we expect you to be adept at core software engineering sk...", "1/ Deep dive with Customer s high level requirements on service onboarding and produce ...", "Required deep expertise in networking, VPC, DirectConnect, ELB, Route 53, Cloud Front, ...", "Experience in creation solutions complying with standards and widely adopted technology...", "Position Description:\u2022 Prepare and present demonstrations of Google\u2019s Cloud services, a...", "Professional experience implementing and managing security systems including: IDS, SIEM...", "We are looking for a Senior Architect Kubernetes to develop and implement a roadmap tow...", "Work directly with product vendor, customer, technical teams, end users and work with d...", "Experience with one of the major cloud providers (Azure / AWS/GCP) as platform and serv...", "Ensure prevention and good management of technical, legal and human security-related ri...", "Educational Qualification : Engineering Must, Candidates with CA background will have a...", "Technical Experience : 1 Deep knowledge in SAP S / 4 HANA for Group reporting 2 Good kn...", "Technical certification in multiple technologies isdesirableSolid understanding of clou...", "This position will gather and refine requirements, develop designs, implement, test and...", "Data on Cloud Architect - Technical understanding of data platform strategy for data on...", "Should be able to work Independently and execute tasks with precisionAWS DevOps Enginee...", "Hands on experience in python and related technologiesExperience in Kubernetes deployme...", "Should be able to work in 24x7 shifts & customer location Should be B E / M E / BSc/MSc...", "Roles and Responsibilities We have an urgent requirement for .Net Senior Solution Archi...", "Job Summary Good skills in Microsoft Azure, and AWS cloud technologies. Domain knowledg...", "Bachelor s Degree in Information Technology or Computer ScienceCertifications that woul...", "Should be able to create solution diagrams, decks, presentation in short notice Should ...", "6+ years of IT Experience.3-5 years experience within an Azure cloud administrator Role...", "Position Overview Siemens is on a mission to enable new business models and ensure a be...", "Having test automation / test data / application / integration testing experience with ...", "Professional Attributes : Stake Holder Management o Stake holder expectation Management...", "KEY PURPOSE OF THE JOB (Position Summary):The Solution Architect for Manipals School of...", "We are looking for a highly skilled and motivated Solution Architect, with experience w...", "Job Description:Neudesic is home to some very smart, talented and motivated people. Peo...", "Good understanding of and experience in working on minimum two or more from Microsoft A...", "Any two or more but CISSP & CEH - mandatory - Hands on experience as an Cyber Security ...", "Experience in creating data lakes for Reporting, AI and Machine LearningTechnical Archi...", "Roles and Responsibilities Candidates must be fluent with real life projectPrimary skil..."], "job_tags": [["SAP", "Consulting", "Microsoft", "Oracle", "Information technology", "Computer science", "Business services", "VMware"], [], ["Hibernate", "Cloud", "Application development", "Monitoring", "SQL", "Automation", "Interpersonal skills", "Configuration management"], ["Unix", "Tomcat", "Linux", "JBoss", "XML", "Weblogic", "Windows", "SQL"], ["CI / CD", "DynamoDB", "ECS", "VPC", "S3", "written", "ALB", "Linux"], ["Business process", "Consulting", "Agile", "Informatica", "SQL", "analytical", "IICS administration", "AWS cloud"], [], ["Business process", "Data migration", "Costing", "Staffing", "Consulting", "Manager Technology", "Presales", "Gap analysis"], [], ["Networking", "IT Infrastructure", "IT services management"], ["Java Architecture", "Microsoft Azure cloud", "Java Microservices", "Technical Architecture", "IT Skills", "J2EE", "Cloud", "HTML"], ["microservice architecture", "IT Skills", "Python", "Cloud", "AWS", "RDS", "S3", "Cloud Trial"], ["Architect", "cloud security", "Networking", "RDBMS", "Web application", "Agile", "application architecture", "Business solutions"], ["Telecom BSS", "IT Skills", "J2EE", "Software Development", "Cloud", "DevOps", "Oracle", "Jenkins"], ["configuration management", "devops", "Cloud Infrastructure Management", "aws", "IT Skills", "Cloud", "Project Management", "BPO"], ["Java", "IT Skills", "J2EE", "Testing", "Cloud", "Oracle", "HTML", "AWS"], ["IT Skills", "Cloud", "AWS", "Computer science", "Front end", "Operational excellence", "Architecture", "Agile"], ["Product management", "Cloud computing", "RDBMS", "TDD", "Software Development Manager", "Agile", "Data structures", "System design"], ["Product management", "Cloud computing", "RDBMS", "TDD", "Software Development Manager", "Agile", "Data structures", "System design"], ["Networking", "Architecture", "Database management", "Cloud", "Python", "AWS", "technical architect"], ["Networking", "RDBMS", "Agile", "Business solutions", "Capacity planning", "cloud security", "SQL database", "Web application"], ["IT Skills", "Java", "Python", "Software Development", "Cloud", "DevOps", "AWS", "Digital architecture experience on cloud AWS and Good programing experience on Python/Java"], ["GCP", "IT Skills", "Python", "Cloud", "DevOps", "Product Management", "rest", "continuous integration"], ["Cloud computing", "Linux", "ISO", "Information security", "Network security", "SIEM", "Windows", "CCNA"], ["Cloud computing", "Load testing", "Coding", "Packaging", "Workflow", "Application development", "HTTP", "Ruby"], ["ML", "CI / CD", "AI", "ML Architecture", "IT Skills", "Cloud", "Architect", "orchestration"], ["IT Skills", "Cloud", "AWS", "Azure", "Computer science", "Automation", "orchestration", "Linux"], ["DevSecOps", "IT Skills", "Software Development", "Cloud", "DevOps", "Hyper-V", "VPN", "CI/CD"], ["SAP BPC", "Business process", "Analytical", "Consulting", "Analytics", "S / 4 HANA", "SAP Analytics", "SAP Business Planning"], ["Business process", "SAP", "Analytical", "Consulting", "Analytics", "SAP S / 4 HANA", "SAP Analytics", "written communication"], ["Kubernetes", "PowerShell", "Terraform", "BASH", "Docker", "Scripting", "Azure", "Helm chart"], ["Azure VPN", "Python", "Azure Automation", "PHP", "Java", "C++", "Azure services", "written"], ["Azure", "IT Skills", "Cloud", "Program Management", "Big Data", "AWS", "IT Consulting", "GCP"], ["AWS", "Linux", "HTTPS", "HTTP", "Monolith", "AWS cloud", "Docker", "cloud services"], ["Restful API", "Azure", "AWS", "python", "Kubernetes", "Azure cloud", "IT Skills", "Cloud"], ["Cloud Solution", "IT Skills", "Java", "Software Development", "C#", "VMware", "SAP", "Cloud Foundry"], ["IT Skills", "AWS", ".Net", "ASP.Net", "C#", ".netcore", "Ef", ".Net Core"], ["Microsoft Azure", "written", "verbal communication", "AWS cloud", "Azure Cloud Native Security", "Azure", "AWS", "IT Skills"], ["Application Virtualization", "IT Skills", "Cloud", "DevOps", "Project Management", "BPO", "project management", "switching"], ["Presales", "Solutioning", "BI", "SaaS", "Data Science", "written", "Analytics", "verbal"], ["Azure", "saas", "Migration", "paas", "Iaas", "Linux", "Azure web apps", "BCP recovery service"], ["Product management", "Solution architecture", "Business process", "Consulting", "Siemens", "E-commerce", "Customer experience", "Information technology"], ["SAP", "Networking", "Presales", "Oracle", "CRM", "Functional testing", "Agile", "Selenium"], ["Costing", "Consulting", "Presales", "Project delivery", "SDLC", "Delivery management", "Staffing", "Time management"], ["Solution Architecting", "Presales", "Solution Design", "Solutioning", "Solution Implementation", "Ideation", "Java", "Agile Methodology"], ["Apex", "IT Skills", "Cloud", "CSS", "Javascript", "Salesforce", "API Integration", "ITIL"], ["Azure Devops", "Kubernetes", "Azure Infrastructure", "PAAS", "Iaas", "Teradata"], ["Solution architecture", "Ubuntu", "Cloud computing", "Network administration", "MCSD", "Linux", "Networking", "PAAS"], ["Solution Architecting", "Cloud Security", "Cyber Security", "Security Architect", "Solution Architect", "Cisa", "Cissp"], ["Python", "IT Skills", "Machine Learning", "Cloud", "Big Data", "AWS", "data architecture", "artificial intelligence"], ["Event Grid", "Azure Functions", "Java", "Stream Analytics", "Azure Logic Apps", "Cosmos Db", "Azure DevOps", "Azure Event Hub"]]}