{"job_title": ["Deputy Manager - Reporting and Data Analysis", "Data Analyst", "Data Management Analyst", "Data Analyst", "Systems Data Analyst", "Data Analyst", "Product and Data Analyst", "Data Analyst", "Data Analyst", "Data Analyst (Statistician)", "Data Analyst, Business Excellence Services", "Data Analyst - Pan india", "Analyst, Third Party Market Data Compliance", "Job Opportunity:: Lead Data Analyst:: Civica India", "Analyst Master Data Management", "Opening For Data Analyst", "Retail Data Analyst", "Data Analyst", "Data Analyst", "Stock Market Data Analyst/ Operator & Secretary Female", "Data Analyst", "DATA ANALYST", "DATA ANALYST", "Data Analyst - Sales Operations", "Operations Data Analyst II", "Lead Analyst, Product Revenue (Data Analyst)", "Operations Analytics /Data Analyst Associate", "Data Analyst", "Business Data Analyst - Marketing", "Business / Data Analyst Analytics", "Business Data Analyst - Marketing", "Intern - Data Scientist", "Data Analyst", "Data Analyst", "Analyst - Data Analytics", "BUSINESS DATA ANALYST - NETWORK DESIGN", "ASSOCIATE - BUSINESS DATA ANALYST", "Reporting Data Analyst", "Data Analyst (tableau/power B.I) consultant", "Data Analyst / Business Analyst", "Operations Data Analyst - Pune India", "Data Analyst", "Data Analyst, Pan India", "Data Analyst", "Salesforce Data Analyst", "Data Analyst Gurugram/Gurgaon/Delhi NCR", "Business / Data Analyst Analytics", "Credit Data Analyst", "Credit Data Analyst", "Data Analyst Manager", "Data Analyst"], "company_name": ["Axa XL", "MomJunction", "A leading Company", "saara", "insightsoftware", "PIRAMAL SWASTHYA MANAGEMENT AND RESEARCH INSTITUTE", "Thinkbridge Software", "DataWENS Technologies", "Hykez Technologies India Pvt. Ltd.", "BUZZBOARD INC", "Ryan, LLC.", "Cigna TTK", "Intercontinental Exchange", "Civica", "Burndy", "A-TRAC ENGINEERING CO LLP", "idfc first bank", "RightWave InfoSolutions (Pvt) Ltd.", "QG EBS Pvt Ltd", "JUNEJA HOTELS PRIVATE LIMITED", "WebMD", "DCB", "DCB", "Skill Lync", "Epiq Systems, Inc.", "cloudneeti", "Global Advertisement Services", "RARR Technologies", "Lennox India Technology Centre", "Grazitti Interactive", "Lennox International", "Tridiagonal Solutions Pvt. Ltd.", "Maxura Academy", "OneMagnify", "Whirlpool", "Lennox India Technology Centre Private Limited", "Lennox India Technology Centre Private Limited", "Confluent", "Anicalls", "RIGHT STEP CONSULTING PRIVATE LIMITED", "PRECISIONxtract", "99Plus IT Solutions", "GyanTU", "SVKMs Narsee Monjee Institute of Management Studies - NMIMS", "FutureSoft (India)", "Benchire", "Grazitti Interactive", "ION", "Reval India Pvt. Ltd.", "VoiceTree Technologies Pvt Ltd.", "Acxiom Technologies"], "company_rating": ["3.7", "Not Found", "Not Found", "Not Found", "Not Found", "4.0", "4.7", "2.7", "5.0", "3.5", "4.5", "3.8", "3.9", "4.0", "3.2", "1.4", "4.0", "5.0", "4.3", "Not Found", "4.5", "4.0", "4.0", "3.5", "4.2", "4.1", "3.3", "Not Found", "4.1", "4.1", "3.0", "3.8", "Not Found", "5.0", "4.3", "4.1", "4.1", "4.0", "4.7", "Not Found", "Not Found", "Not Found", "Not Found", "Not Found", "3.7", "4.6", "4.1", "3.6", "5.0", "3.2", "4.6"], "company_review_count": ["(198 Reviews)", "Not Found", "Not Found", "Not Found", "Not Found", "(212 Reviews)", "(38 Reviews)", "(6 Reviews)", "(4 Reviews)", "(14 Reviews)", "(241 Reviews)", "(150 Reviews)", "(54 Reviews)", "(70 Reviews)", "(16 Reviews)", "(4 Reviews)", "(4832 Reviews)", "(4 Reviews)", "(8 Reviews)", "Not Found", "(14 Reviews)", "(1831 Reviews)", "(1831 Reviews)", "(114 Reviews)", "(78 Reviews)", "(113 Reviews)", "(33 Reviews)", "Not Found", "(56 Reviews)", "(68 Reviews)", "(9 Reviews)", "(18 Reviews)", "Not Found", "(2 Reviews)", "(1200 Reviews)", "(56 Reviews)", "(56 Reviews)", "(2 Reviews)", "(2 Reviews)", "Not Found", "Not Found", "Not Found", "Not Found", "Not Found", "(144 Reviews)", "(2 Reviews)", "(68 Reviews)", "(7 Reviews)", "(2 Reviews)", "(23 Reviews)", "(14 Reviews)"], "experience": ["3-5 Yrs", "2-3 Yrs", "2-5 Yrs", "1-6 Yrs", "3-5 Yrs", "3-7 Yrs", "3-7 Yrs", "2-5 Yrs", "3-5 Yrs", "1-6 Yrs", "2-4 Yrs", "1-4 Yrs", "4-7 Yrs", "5-8 Yrs", "4-6 Yrs", "3-8 Yrs", "2-5 Yrs", "3-8 Yrs", "4-8 Yrs", "3-6 Yrs", "6-9 Yrs", "2-5 Yrs", "2-5 Yrs", "2-5 Yrs", "4-8 Yrs", "3-6 Yrs", "3-8 Yrs", "5-8 Yrs", "3-5 Yrs", "2-5 Yrs", "2-5 Yrs", "0-1 Yrs", "2-6 Yrs", "1-3 Yrs", "3-6 Yrs", "2-5 Yrs", "2-5 Yrs", "3-5 Yrs", "5-8 Yrs", "2-3 Yrs", "1-2 Yrs", "2-5 Yrs", "3-5 Yrs", "3-5 Yrs", "4-8 Yrs", "2-5 Yrs", "2-5 Yrs", "1-4 Yrs", "1-3 Yrs", "8-15 Yrs", "1-3 Yrs"], "salary": ["6,00,000 - 12,00,000 PA.", "Not disclosed", "Not disclosed", "Not disclosed", "Not disclosed", "3,00,000 - 6,50,000 PA.", "7,00,000 - 15,00,000 PA.", "Not disclosed", "Not disclosed", "Not disclosed", "Not disclosed", "Not disclosed", "Not disclosed", "50,000 - 3,00,000 PA.", "Not disclosed", "2,00,000 - 3,00,000 PA.", "Not disclosed", "Not disclosed", "4,00,000 - 7,00,000 PA.", "Not disclosed", "Not disclosed", "Not disclosed", "Not disclosed", "Not disclosed", "Not disclosed", "Not disclosed", "Not disclosed", "Not disclosed", "Not disclosed", "Not disclosed", "Not disclosed", "Not disclosed", "3,50,000 - 7,50,000 PA.", "Not disclosed", "12,00,000 - 16,00,000 PA.", "Not disclosed", "Not disclosed", "Not disclosed", "Not disclosed", "Not disclosed", "Not disclosed", "Not disclosed", "Not disclosed", "Not disclosed", "Not disclosed", "Not disclosed", "Not disclosed", "Not disclosed", "Not disclosed", "Not disclosed", "Not disclosed"], "location": ["Gurgaon/Gurugram", "Hyderabad/Secunderabad\n(WFH during Covid)", "Chennai", "remote", "Hyderabad/Secunderabad", "Lucknow", "India", "Chennai", "Kolkata", "Remote", "Hyderabad/Secunderabad", "Remote", "Hyderabad/Secunderabad", "Vadodara", "Kochi/Cochin, Ernakulam", "Mumbai(Bandra Kurla Complex), Mumbai Suburban, Mumbai (All Areas)", "Mumbai", "Noida", "Noida, Ghaziabad, Delhi / NCR", "Gurgaon/Gurugram", "Mumbai", "Mumbai", "New Delhi", "Chennai", "Pune", "Gurgaon/Gurugram", "Pune", "Mumbai, Pune, Chennai", "Chennai", "Mohali, Panchkula", "Chennai", "Pune", "Kolkata", "Chennai", "Pune", "Chennai", "Chennai", "Bangalore/Bengaluru", "Chennai", "Gurgaon", "Pune", "Vadodara", "remote", "Mumbai", "Chennai", "Gurgaon/Gurugram, Delhi / NCR", "Mohali", "Mumbai", "Mumbai", "Remote", "remote"], "job_description": ["Participate in projects as required to ensure that all potential impacts to financial d...", "Prior experience of working with Digital Marketing reporting tools like Google Data Stu...", "This role is opened for Women comeback programme who have career break and wanted to co...", "Good knowledge and experience in Advanced MS Excel 1+ years of proven working experienc...", "The Systems Data Analyst position is responsible for ensuring customer, vendor, and pro...", "CANDIDATES FROM DEVELOPMENT SECTOR BACKGROUND WILL BE GIVEN PREFERENCEPurpose of the ro...", "Proven experience working with product and design teams to formulate requirements and m...", "Bachelors degree in a STEM or business-related discipline or greater than 1 year of rel...", "Bachelors or above in quantitative discipline: Statistics, Applied Mathematics, Economi...", "Should have worked on tracking and analyzing data for web and / or mobile appsProven wo...", "Duties and Responsibilities: People: Maintains a professional and positive attitude; be...", "We are looking for a Data analyst who will be part of the Cigna s European Actuarial Re...", "Proficiency in the standard Microsoft Office suite (Excel, Word, Access)Experience in m...", "Identifying, preparing, interpreting and resolving data issues. Triage incoming tickets...", "Should be flexible to work in night shiftAs a member of Master Data Management (MDM) te...", "Designing, monitoring, analyzing & troubleshooting reports & data analysis systems. Int...", "Graduate - Any Post Graduate - Any 5 Years of experience", "Any experience on automated reporting tools like PowerBI, Google analytics is preferred...", "BTECH/ MTECH degree from a renowned university/ college Qualification, Experience & Ski...", "Part time / full time Stock Market Data Analyst/ operator & secretary femalePartly work...", "Proficient with Microsoft Excel (including pivots, formulas, and macros) and PowerPoint...", "Responsbile for development of inhouse applications and customization of Core banking M...", "Responsbile for development of inhouse applications and customization of Core banking M...", "Roles and Responsibilities: Daily real-time monitoring of service levels for all queues...", "Must be flexible and be available to work some evening and weekend shifts Bachelor s de...", "Bachelors or master s degree in Computer Science/ Management/ Statistics or related fie...", "Strong analytical skills and attention to detail -Ability to multi-task and assist the ...", "Proven self-motivation to take initiative and master new tasks quickly Experience in da...", "Deep experience in extracting, cleaning, preparing and modeling data Bachelors degree i...", "Should design, develop, test, and deploy Power BI scripts and perform detailed analytic...", "Deep experience in extracting, cleaning, preparing and modeling data Bachelors degree i...", "Essential Duties and Key Competencies : A Chemical Engineer / analysts with comprehensi...", "Using specialist tools to extract the data needed. Responding to data-related queries a...", "Academic degree BE Mechanical or Automobile /CA Inter / ICWA Inter / MBA in Finance fro...", "Roles and Responsibilities Job ResponsibilitiesTrack global spend data, develop spend a...", "Any graduation with 4 to 6 years of experience in Network Design in SCM domain Addition...", "Bachelor s in computer science, statistics, applied mathematics, data management, infor...", "Hands-on experience developing and maintaining dashboards in Tableau and Tableau Server...", "Must be able to manage multiple tasks in a fast-paced, dynamic work environment Experie...", "PG:Any Postgraduate - Any SpecializationMinimum work experience of 2 - 3 years in Data ...", "2 years experience (relevant internships will be considered) Bachelor s degree required...", "Experience of 3- 5 years as a Data Analyst Experience in data- driven problem solving. ...", "Responsibilities Design and implement effective database solutions and models to store ...", "Previous experience working as a Data Analyst or similar domain in an education institu...", "Added advantage will be experience with any programming languages such as .NET C# and V...", "Bachelor in Engineering with at least 2+ years of hands-on experience as a data analyst...", "Should design, develop, test, and deploy Power BI scripts and perform detailed analytic...", "Reliable, helpful and a good team member", "Key responsibilities Enter borrowers quarterly financial statements and accounts into s...", "Proficient in advance excel, SQL / Python/R / Advance Excel3 years of experience in dat...", "The Data Analyst will work independently to prepare data to be used for building models..."], "job_tags": [["sql", "excel", "Data distraction", "data analysis", "MS Access", "Power Bi", "MS SQL Server", "Data Extraction"], ["predictive modeling", "logistic regression", "Cluster Analysis"], ["Data analyst", "Data Management Analyst", "Investment Banking", "data management", "Banking", "Data Analysis", "Data Maintenance", "Data Analytics"], ["Machine Learning", "analytical", "NoSQL", "communication", "MS Excel", "SQL", "Python", "Automation"], ["Manager Quality Assurance", "Data management", "Project management", "Analytical", "Customer support", "Operations", "Monitoring", "SQL"], ["Python"], ["data analytics", "Product Analysis", "language R", "Power Bi", "Python"], ["Excel", "Reporting Tools", "CRM", "SQL", "arrays", "PowerPoint", "analytical", "RDBMS"], ["Pandas", "verbal", "written communication", "Python", "written", "Hadoop", "analytics", "R"], ["Business objects", "SAS", "Process improvement", "XML", "Data collection", "Manager Quality Control", "SPSS", "Information management"], ["Computer science", "Data analysis", "Excel", "Process improvement", "Analytical", "Reconciliation", "Billing", "Datastage"], ["data cleansing", "Claims", "Underwriting", "Machine learning", "Business planning", "Actuarial", "Data quality", "Data Analyst"], ["remediation", "Usage", "Compliance", "Contract management", "External audit", "Analytical", "Billing", "market data"], ["Data Analysis", "SQL Queries", "Crystal Report", "SQL Server"], ["master data management", "SAP MDM"], ["Excel", "Data Analytics"], ["Stress testing", "Audit compliance", "Regulatory reporting", "Banking", "Retail lending", "Data Analyst", "IFRS", "Forecasting"], ["Process design", "Google Analytics", "Linguistics", "Market research", "EMC", "Data quality", "Reporting tools", "CRM"], ["excel", "data analysis", "SAP", "data mining", "Word", "ERP", "MS Office", "Power point"], ["Stock Broking", "Stock Market Operations", "Stock Market Analysis", "data analysis", "stock market", "market data", "Secretary Female"], ["Google Analytics", "Excel", "MS Access", "Web analytics", "Content optimization", "Web development", "Omniture", "Data analytics"], ["Relationship", "Data Analyst", "Management", "Core banking"], ["Relationship", "Data Analyst", "Management", "Core banking"], ["Excel", "Sales operations", "Analytical", "Operations", "RTA", "Monitoring", "SQL", "Business operations"], ["Basic", "Excel", "data manipulation", "Project management", "Workflow", "Data Analyst", "Analyst II", "MS Office"], ["Computer science", "Product management", "tableau", "Focus", "Manager Technology", "Data analytics", "Data Analyst", "Lead Analyst"], ["Financial Analysis", "Data Analysis", "MIS Reporting", "Analytics", "WFM"], ["data analysis", "Power BI", "Confluence", "MS Office", "written", "Big Data", "verbal communication", "Data Visualization"], ["Alteryx", "MATLAB", "Tableau", "STATA Microsoft Office", "predictive modeling", "PowerPoint", "requirements gathering", "Qlik"], ["IT Skills", "Quality Assurance", "Power BI", "IT services", "Data analysis", "SAS", "Social media", "SSRS"], ["Computer science", "Data analysis", "Operations research", "SAS", "Business analytics", "Predictive modeling", "SPSS", "Data mining"], ["Mining", "Data management", "Pharma", "Consulting", "Machine learning", "Troubleshooting", "MATLAB", "SQL"], ["Data Anlalytics", "Research Analysis", "Data Analysis"], ["Data Analyst"], ["Bi", "Business Intelligence", "Logistic Regression", "sap", "Data Studio", "regression analysis", "cost modelling", "Tableau"], ["Network design", "Business Data Analyst", "SCM"], [], [], ["PowerBI", "Alteryx", "Tableau", "Cognos", "ETL", "SAS", "Microsoft Office Suite", "Data management"], ["Data dictionary", "Excel", "Data management", "Business Analyst", "Data Analyst", "MS Office", "Business intelligence", "Software services"], [], ["Data Analyst"], [], ["Data analysis", "Excel", "Sales", "Business analytics", "Analytical", "Data collection", "MS Office tools", "Packaging"], ["databases", "integration", "VB", "ASP", "CSS", "Salesforce", "AJAX", "SQL"], [], ["IT services", "Data analysis", "SAS", "SSRS", "SSIS", "Business intelligence", "Adobe", "Analytics"], ["Excel", "Supply chain", "Financial statements", "Usage", "Financial accounting", "Fixed income", "Finance", "Workflow"], ["Excel", "Supply chain", "Financial statements", "Usage", "Financial accounting", "Fixed income", "Finance", "Workflow"], ["Data analysis", "Automation", "Data collection", "data integrity", "Data analytics", "Data Analyst", "Business intelligence", "WiFi"], []]}