{"job_title": ["Senior Software Engineer", "UX Designer", "React JS Developer", "MEAN Stack Developer", "ARIS Developer", "IT Consulting Professional", "Programmer Analyst (WPF, .NET)", "ARIS Developer", "Java / .Net / Oracle Plsql / Mainframe / Angular / Devops Developer", "Java / .Net / Oracle Plsql / Mainframe / Angular", "SAP UI5 Consultant", "HTML, CSS, JavaScript Developer", "Java / .Net / Oracle Plsql / Mainframe / Angular / Devops Developer", "Java / .Net / Oracle Plsql / Mainframe / Angular / Devops Developer", "Java Full stack Developer", "UI Developer (Angular / ReactJS / NodeJS)", "Product Manager", "Siebel Developer", "UI Developer - Advanced", "UI Engineer III", "AWS/Azure/GCP Consultant", "Ember JS Developer", "PHP Developer", "IT Delivery Professional", "Senior Software Engineer - UI Developer", "Sr. Software Engineer I", "Senior Software Engineer", "Software Engineer", "Associate Software Engineering Manager - Facets", "Backend Java Developer", "Databricks Unified Analytics Platform Application Lead", "Pegasystems Platform Application Developer", "Pegasystems Platform Application Developer", "Pegasystems Platform Application Developer", "Pegasystems Platform Application Developer", "Salesforce Lightning Web Components Application Developer", "Application Developer: Adobe Marketing & Analytics", "Application Developer: Red Hat Cloud Modernization", "Data Engineer: Big Data", "UI Lead", "ETL Testing | 5-10 Yrs | Bangalore", "Solution Architect Technical Lead - RPA Automation", "Senior Software Engineer", "API Regression Automation | 5-10 Yrs | Bangalore", "Great Opportunity - Immediate Joiner - AI/ML - MSys Technologies", "Android Developer", "Software Engineer", "Android Developer", "Software Engineer", "Junior Developer", "Senior Software Engineer - IOS (C , Networking)"], "company_name": ["Mphasis", "Adore Technosoft (OPC) Pvt Ltd", "Infosys", "Infosys", "Infosys", "Infosys", "Quantum Phinance Pvt. Ltd", "Infosys", "Infosys", "Infosys", "Infosys", "Infosys", "Infosys", "Infosys", "Infosys", "Infosys", "Maxdata Solutions", "Zebra Technologies", "Zebra Technologies", "Flipkart", "Infosys", "Infosys", "Infosys", "Infosys", "Optum", "Optum", "Optum", "Optum", "Optum", "Encora", "Accenture", "Accenture", "Accenture", "Accenture", "Accenture", "Accenture", "IBM", "IBM", "IBM", "Genisys Information Systems", "TechStar Group", "Prodapt Solutions", "Nitor", "TechStar Group", "MSys Technologies", "O2H Management Services", "D'source", "D'source", "D'source", "Busisol Sourcing India Pvt Ltd", "Zscaler Softech"], "company_rating": ["3.8", "3.2", "3.9", "3.9", "3.9", "3.9", "4.1", "3.9", "3.9", "3.9", "3.9", "3.9", "3.9", "3.9", "3.9", "3.9", "Not Found", "4.2", "4.2", "4.2", "3.9", "3.9", "3.9", "3.9", "4.1", "4.1", "4.1", "4.1", "4.1", "4.1", "4.2", "4.2", "4.2", "4.2", "4.2", "4.2", "4.2", "4.2", "4.2", "3.6", "4.0", "3.8", "3.0", "4.0", "3.9", "5.0", "Not Found", "Not Found", "Not Found", "Not Found", "4.1"], "company_review_count": ["(4587 Reviews)", "(11 Reviews)", "(26348 Reviews)", "(26348 Reviews)", "(26348 Reviews)", "(26348 Reviews)", "(13 Reviews)", "(26348 Reviews)", "(26348 Reviews)", "(26348 Reviews)", "(26348 Reviews)", "(26348 Reviews)", "(26348 Reviews)", "(26348 Reviews)", "(26348 Reviews)", "(26348 Reviews)", "Not Found", "(61 Reviews)", "(61 Reviews)", "(10454 Reviews)", "(26348 Reviews)", "(26348 Reviews)", "(26348 Reviews)", "(26348 Reviews)", "(1940 Reviews)", "(1940 Reviews)", "(1940 Reviews)", "(1940 Reviews)", "(1940 Reviews)", "(141 Reviews)", "(30495 Reviews)", "(30495 Reviews)", "(30495 Reviews)", "(30495 Reviews)", "(30495 Reviews)", "(30495 Reviews)", "(20453 Reviews)", "(20453 Reviews)", "(20453 Reviews)", "(71 Reviews)", "(48 Reviews)", "(373 Reviews)", "(2 Reviews)", "(48 Reviews)", "(53 Reviews)", "(2 Reviews)", "Not Found", "Not Found", "Not Found", "Not Found", "(113 Reviews)"], "experience": ["4-6 Yrs", "7-8 Yrs", "5-10 Yrs", "2-7 Yrs", "2-7 Yrs", "2-7 Yrs", "1-2 Yrs", "2-7 Yrs", "3-5 Yrs", "1-3 Yrs", "2-7 Yrs", "2-7 Yrs", "3-8 Yrs", "1-3 Yrs", "2-7 Yrs", "1-6 Yrs", "2-6 Yrs", "2-5 Yrs", "6-8 Yrs", "2-4 Yrs", "9-14 Yrs", "5-10 Yrs", "2-7 Yrs", "5-8 Yrs", "3-8 Yrs", "7-10 Yrs", "5-8 Yrs", "4-8 Yrs", "8-13 Yrs", "7-12 Yrs", "4-6 Yrs", "4-6 Yrs", "4-6 Yrs", "4-6 Yrs", "6-8 Yrs", "4-6 Yrs", "10-15 Yrs", "3-7 Yrs", "2-5 Yrs", "5-7 Yrs", "5-10 Yrs", "5-7 Yrs", "3-6 Yrs", "5-10 Yrs", "5-8 Yrs", "2-4 Yrs", "1-3 Yrs", "3-5 Yrs", "2-4 Yrs", "3-5 Yrs", "3-6 Yrs"], "salary": ["Not disclosed", "Not disclosed", "Not disclosed", "Not disclosed", "Not disclosed", "Not disclosed", "Not disclosed", "Not disclosed", "Not disclosed", "Not disclosed", "Not disclosed", "Not disclosed", "Not disclosed", "Not disclosed", "Not disclosed", "Not disclosed", "Not disclosed", "Not disclosed", "Not disclosed", "Not disclosed", "Not disclosed", "Not disclosed", "Not disclosed", "Not disclosed", "Not disclosed", "Not disclosed", "Not disclosed", "Not disclosed", "Not disclosed", "Not disclosed", "Not disclosed", "Not disclosed", "Not disclosed", "Not disclosed", "Not disclosed", "Not disclosed", "Not disclosed", "Not disclosed", "Not disclosed", "Not disclosed", "Not disclosed", "Not disclosed", "Not disclosed", "Not disclosed", "Not disclosed", "Not disclosed", "Not disclosed", "Not disclosed", "Not disclosed", "Not disclosed", "Not disclosed"], "location": ["Bangalore/Bengaluru", "Hyderabad/Secunderabad, Delhi / NCR, Bangalore/Bengaluru", "Bangalore/Bengaluru", "Bangalore/Bengaluru", "Hyderabad/Secunderabad", "Hyderabad/Secunderabad", "Mumbai", "Chennai", "Indore", "Mohali", "Bangalore/Bengaluru", "Pune", "Mangaluru/Mangalore", "Pune", "Pune", "Bangalore/Bengaluru", "Bangalore/Bengaluru", "Bangalore/Bengaluru", "Bangalore/Bengaluru", "Bangalore/Bengaluru", "Bangalore/Bengaluru", "Pune", "Chennai", "Hyderabad/Secunderabad", "Hyderabad/Secunderabad", "Bangalore/Bengaluru", "Chennai", "Hyderabad/Secunderabad", "Bangalore/Bengaluru", "Bangalore/Bengaluru", "Bangalore/Bengaluru", "Hyderabad/Secunderabad", "Hyderabad/Secunderabad", "Bangalore/Bengaluru", "Hyderabad/Secunderabad", "Jaipur", "Bangalore/Bengaluru", "Chennai", "Kochi/Cochin", "Bangalore/Bengaluru\n(WFH during Covid)", "Bangalore/Bengaluru", "Chennai, Bangalore/Bengaluru", "Pune", "Bangalore/Bengaluru", "Pune, Chennai, Bangalore/Bengaluru\n(WFH during Covid)", "Ahmedabad", "Nasik/Nashik", "Mumbai", "Nasik/Nashik", "Chennai", "Bangalore/Bengaluru"], "job_description": ["Who are we looking for?We are looking for a Senior Developer for Windows desktop applic...", "Experience in Agile / Scrum approachWorks closely with user experience team in design o...", "MCA, MSc, Bachelor of Engineering Good understanding of the technology and domain Analy...", "MCA, MSc, Bachelor of Engineering Good understanding of SDLCDigital Experience", "ResponsibilitiesA day in the life of an Infoscion\u2022 As part of the Infosys consulting te...", "Technical and Professional Requirements: Must have bachelors or equivalent degree, with...", "Good to have skills : Modern C++, Templates, v11 new features etc, Good understanding o...", "ResponsibilitiesA day in the life of an Infoscion\u2022 As part of the Infosys consulting te...", "Bachelor of Engineering Good understanding of SDLC and agile methodologies", "Bachelor of Engineering Good understanding of SDLC and agile methodologies", "Technical and Professional Requirements: Must have bachelors or equivalent degree, with...", "MCA, MSc, Bachelor of Engineering Good understanding of SDLCDigital Experience", "Bachelor of Engineering Good understanding of SDLC and agile methodologies", "Bachelor of Engineering Good understanding of SDLC and agile methodologies", "MCA, MSc, Bachelor of Engineering Good understanding of SDLCDigital Experience", "Bachelor of Engineering Good understanding of SDLC and agile methodologies", "2+ years of hands-on experience in Product Management and proven track record of managi...", "Minimum of 2-5 years of experience in Siebel developmentVery good knowledge on Siebel O...", "Bachelor s / Masters degree major in Computer Science Experience developing a Progressi...", "What UI Engineers @ Cleartrip do? Build next-generation web applications which are effi...", "ResponsibilitiesUnderstand requirements and client\u2019s cloud maturity and define viable s...", "Bachelor of Engineering, Master Of CompGood understanding of the technology and domain ...", "Bachelor of Engineering, MTech, MCA Digital ExperienceGood understanding of SDLC", "Bachelors or Masters in Engineering or related technical field (Computer science)Data-S...", "Participate and contribute in Architecture discussion with Architects, Product Owners, ...", "Combine two of the fastest-growing fields on the planet with a culture of performance, ...", "Must Haves: - Education: Bachelors Degree in a technical field 5- 8 years of profession...", "Primary Responsibilities:Business Knowledge:Capable of acquiring the full business know...", "Primary Responsibilities:Be able to understand HLD& LLD documentsBe able to translate t...", "Experience in web application application servers - Tomcat etcExperience in testing too...", "15 years of full time education Educational Qualification : a: Engineering graduate pre...", "Key Responsibilities : 1 Experience in implementing Pega applications2 Participated in ...", "Project Role : Application Developer Project Role Description : Design, build and confi...", "Professional Attributes : 1 Communication should be good and able to handle client call...", "Work Experience : 6-8 years Professional Attributes : Good communication and analytical...", "Educational Qualification : Bachelor of Engineering preferred Computer Science or IT15 ...", "Understanding client s technical ecosystem, its requirement and provide enterprise solu...", "As an Application Developer, you will lead IBM into the future by translating system re...", "In-depth experience in modern data platform components such as the Hadoop, Hive, Pig, S...", "Greetings from Genisys Group!!!!!!Location: BangaloreExperience: 5 - 7 YearsKey Require...", "Experience in engaging with Product Managers, Developers, Business Analysts, Design Arc...", "BluePrism(Preferred) and Distinctive problem-solving, strategic and analytical capabili...", "Experience of working with relational (Postgres)and NoSQL databaseGood understanding of...", "Roles and Responsibilities Greetings from TechStar!!This is with regards to an excellen...", "Proven experience as a Machine Learning Engineer or similar role", "Proven experience as a Android developer / hybrid mobile develperExcellent analytical s...", "Responsibilities : Design and Develop Software as per standard. -UI designing is needed...", "Proficient understanding of code versioning tool, such as GitAt least 3 to 5 years of e...", "ASP.NET, Good Communication, HTML, MVC, MySQL", "Ability to work and thrive in a fast-paced environment, learn rapidly and master divers...", "The Mobile team at Zscaler is responsible for developing a cross-platform client applic..."], "job_tags": [["C++", "Test-Driven Development", "C++ Development", "Product Engineering", "Windows Presentation Foundation"], ["Visual Design", "Scrum", "presentation", "Visual Design Principles", "Miro", "Adobe InDesign", "methodologies", "Sketch"], ["React JS", "IT Skills", "Testing", "Quality Assurance", "redux", "React native", "debugging", "software quality assurance"], ["MEAN Stack", "UI", "Analytical", ">MEAN Stack", "SDLC", "Software Engineering"], ["Business Process Management", "IT Skills", "Java", "MS Visio", "ARIS", "Signavio", "Agile", "CI/CD"], ["IT Consulting", "IT Skills", "Software Development", "Cloud", "Node.js", "Javascript", "SAP", "SAP Fiori"], ["WPF", "Windows Service", "Web API", "communication", "Git", "SQL queries", "ASP NET", "UI"], ["ARIS", "IT Skills", "Java", "Business Process Management", "Process Consulting", "ARIS Developer", "Continuous Integration", "Business Process Modeling"], ["Java", "IT Skills", "DevOps", "Oracle", "AWS", ".Net", "Azure", "AWS DevOps"], ["Java", "PL/SQL", "ReactJS", "Oracle", "AWS", "Devops", "NodeJS", "Angular"], ["SAP UI5", "Fiori Design patterns", "Fiori Launchpad", "SAPUI5", "UI Theme designer", "HTML5", "JavaScript", "Fiori"], ["HTML", "IT Skills", "Angularjs", "CSS", "Javascript", "Angular 8", "Angular 6", "Angular.JS"], ["Java", "IT Skills", "DevOps", "Oracle", "AWS", ".Net", "Azure", "Oracle PL/SQL"], ["Java", ".Net", "Oracle", "IT Skills", "DevOps", "Mainframe", "AWS", "Azure"], ["Java", "SDLC", "UI", "Analytical", "IT Skills", "Software Engineering", "Programming"], ["Angular", "ReactJS", "problem solving", "engineering", "NodeJS", "SDLC"], ["Product Manager", "Product Launch", "IT Skills", "Product Management", "Product Strategy", "SAAS", "Agile", "Scrum"], ["Siebel", "Open UI Development", "RESTful services", "Webservices", "Siebel development", "EAI", "Siebel Objects", "SOAP"], ["UI", "TypeScript", "REST API", "CSS", "JavaScript", "Agile", "HTML", "NgRx"], ["Front end", "Web technologies"], ["AWS", "IT Skills", "Java", "Python", "Cloud", ".Net", "Azure", "NoSQL"], ["Ember JS", "agile methodologies", "Project life cycle", "debugging", "Analytical", "communication", "IT Skills", "Testing"], ["PHP", "UI", "Analytical", "Markup Language", ">PHP", "UI & Markup Language", "SDLC", "IT Skills"], ["Java", "IT Skills", "Quality Assurance", "Node.js", "Javascript", "redux", "Express JS", "MySQL"], ["UI", "IT Skills", "Java", "J2EE", "Cloud", "DevOps", "Project Management", "Javascript"], ["Azure", "IT Skills", "Machine Learning", "Cloud", "DevOps", "HTML", "CSS", "Javascript"], [".NET", "IT Skills", "Software Development", "Testing", "ASP.Net", "C#", "PL/SQL", "GIT"], ["SQL", "JMockit", "REST Architecture", "Sprint Boot", "GitHub", "Node.js", "Fortify", "RabbitMQ"], ["Facets", "IT Skills", "Oracle", "PL/SQL", "Production support", "Software Engineering", "CMS", "Kafka"], ["Java", "Jenkins", "SOAP UI", "Agile Development", "J2SE", "Tomcat", "JUnit", "Gradle"], ["Computer science", "Consulting", "SQL", "Python", "Data extraction", "communication", "Hadoop", "Spark SQL"], ["Coding", "Consulting", "Application development", "Pega", "Customer service", "Business process", "Performance management", "Project initiation"], ["Business process", "Consulting", "HTTP", "Pega", "Test cases", "Clipboard", "Live - UI", "Integration SOAP"], ["Consulting", "Application development", "HTTP", "Pega", "Test cases", "REST", "Clipboard", "Communication"], ["Business process", "JMS", "Consulting", "Pega", "Agile methodology", "Analytical skills", "PRPC", "Routing"], ["Coding", "Consulting", "Javascript", "Scrum", "Salesforce", "CSS", "Aura", "Apex coding"], ["jQuery", "Javascript", "HTML", "Adobe", "Analytics", "IT Skills", "CSS", "Tableau"], ["Unix", "Web services", "Networking", "Conceptualization", "Python", "IT Skills", "Java", "Testing"], ["Automation", "Coding", "Javascript", "Agile", "SDLC", "IT Skills", "Java", "Python"], ["Node.Js", "React.Js", "React JS", "ANT", "Maria DB", "HTML", "Node JS", "AWS Deployment"], ["ETL Testing", "Python", "SQL", "Azure Devops"], ["uipath", "IT Skills", "RPA", "organization skills", "design", "UI Path", "problem-solving", "time-management"], ["JDK", "Elastic Search", "Angular", "Java", "Kafka", "Hadoop", "Web UI Development", "Postgres"], ["Specflow", "API", "Azure Devops", "IT Skills", "Python", "SQL"], ["Machine Learning", "artificial intelligence"], ["Analytical skills", "Programming", "Android"], ["ERP", "MS SQL", "Content management", "Web technologies", "MySQL", "SMS", "Javascript", "Design development"], ["IT services", "Service management", "Performance tuning", "Automation", "GIT", "Mobile development", "MVVM", "Android SDK"], ["Automation", "Front end", "Simulation", "Coding", "MySQL", "Debugging", "HTML", "WCF"], ["jQuery", "Linux", "MySQL", "Javascript", "Database administration", "HTML", "Apache", "SQL"], ["Performance tuning", "Networking protocols", "Linux", "VPN", "Network security", "Unit testing", "Windows", "Mac Os"]]}